fontpls/__init__.py
fontpls/__main__.py
fontpls/cli.py
fontpls/downloader.py
fontpls/extractors/__init__.py
fontpls/extractors/html_extractor.py
fontpls/templates/__init__.py
fontpls/templates/css.py
fontpls/templates/html.py
fontpls/utils/__init__.py
fontpls/utils/font.py
fontpls/utils/logging.py
fontpls/utils/url.py
tests/__init__.py
tests/test_cli.py
tests/test_downloader.py
tests/test_font_utils.py
tests/test_html_extractor.py
tests/test_templates.py
tests/test_url_utils.py
fontpls-0.1.0.dist-info/LICENSE
fontpls-0.1.0.dist-info/METADATA
fontpls-0.1.0.dist-info/WHEEL
fontpls-0.1.0.dist-info/entry_points.txt
fontpls-0.1.0.dist-info/top_level.txt
fontpls-0.1.0.dist-info/RECORD
