Metadata-Version: 2.1
Name: fontpls
Version: 0.1.0
Summary: A CLI tool to download fonts used on a website
Home-page: https://github.com/jon-becker/fontpls
Author: Jon-Becker
Author-email: jonathan@jbecker.dev
Classifier: Programming Language :: Python :: 3
Classifier: License :: OSI Approved :: MIT License
Classifier: Operating System :: OS Independent
Requires-Python: >=3.8
License-File: LICENSE
Requires-Dist: requests
Requires-Dist: beautifulsoup4
Requires-Dist: cssutils
Requires-Dist: fonttools
Requires-Dist: brotli
Provides-Extra: dev
Requires-Dist: pytest>=7.0.0; extra == "dev"
Requires-Dist: pytest-cov>=2.12.0; extra == "dev"
Requires-Dist: black>=21.5b2; extra == "dev"
Requires-Dist: pytest; extra == "dev"
Requires-Dist: pytest-cov; extra == "dev"
